circulus/__init__.py
circulus/cstatistics.py
core/__init__.py
core/ants.py
core/antslogger.py
core/antsplatform.py
core/antstimeseries.py
extractor/__init__.py
extractor/caller.py
painter/__init__.py
painter/plots.py
postprocessing/__init__.py
postprocessing/power.py
postprocessing/scale.py
preparator/__init__.py
preparator/dirprep.py
preprocessing/__init__.py
preprocessing/downsampling.py
preprocessing/filters.py
preprocessing/normalization.py
spikes/__init__.py
spikes/classification.py
timefrequency/__init__.py
timefrequency/fft.py
timefrequency/multitaper.py
timefrequency/wavelet.py
ants_pi-0.0.4.dist-info/LICENSE
ants_pi-0.0.4.dist-info/METADATA
ants_pi-0.0.4.dist-info/WHEEL
ants_pi-0.0.4.dist-info/top_level.txt
ants_pi-0.0.4.dist-info/RECORD
