Metadata-Version: 2.1
Name: ants-pi
Version: 0.0.4
Summary: ANalysis for Time Series
Home-page: https://github.com/minsmis/ANTS
Author: neuraldevops
Author-email: minseok.kim@brain.snu.ac.kr
Project-URL: Bug Tracker, https://github.com/minsmis/ANTS/issues
Classifier: Programming Language :: Python :: 3.10
Classifier: License :: OSI Approved :: MIT License
Classifier: Operating System :: OS Independent
Requires-Python: >=3.10
License-File: LICENSE
Requires-Dist: mat73 >=0.62
Requires-Dist: matlabengine >=23.2.1
Requires-Dist: matplotlib >=3.7.2
Requires-Dist: numpy >=1.26.0
Requires-Dist: pandas >=2.1.1
Requires-Dist: pyside6 >=6.6.0
Requires-Dist: scikit-learn >=1.3.0
Requires-Dist: scipy >=1.11.1
